dependency_sdk/__init__.py
dependency_sdk/formula.py
dependency_sdk/main.py
dependency_sdk-1.0.3.dist-info/LICENSE
dependency_sdk-1.0.3.dist-info/METADATA
dependency_sdk-1.0.3.dist-info/WHEEL
dependency_sdk-1.0.3.dist-info/top_level.txt
dependency_sdk-1.0.3.dist-info/RECORD
